{
  "brand": "BMW",
  "tier": "adjacent",
  "url": "https://bmw.com",
  "fetched_at": "2026-03-18T15:50:01.785893+00:00",
  "extraction_failed": false,
  "js_heavy": true,
  "elements": {
    "title": "BMW.com | The international BMW Website",
    "meta_description": null,
    "og_description": null,
    "h1": "Sheer Driving Pleasure",
    "hero_subheadline": null,
    "h2s": [
      "ALL BMW MODELS",
      "Quick Links",
      "More BMW Websites",
      "BMW.com",
      "Visit us on",
      "Looking for the right experience?"
    ],
    "ctas": [
      "Find your BMW",
      "Home",
      "BMW in your country",
      "BMW Group Careers",
      "EU Detergents Regulation",
      "REACH Regulation",
      "Compatibility Check",
      "Connected Test Vehicle",
      "Cooperation Test Car",
      "EU Battery Regulation",
      "Parking Test Car",
      "Recalls and Technical Updates",
      "BMW M",
      "BMW M Motorsport",
      "BMW Golfsport",
      "BMW M Driving Experience",
      "BMW Welt",
      "BMW Group Classic",
      "BMW Corporate/Direct Sales",
      "BMW Group",
      "BMW Group Cultural Engagement",
      "BMW ConnectedDrive Upgrades",
      "Contact",
      "Cookies",
      "Imprint",
      "Legal Notice / Data protection",
      "Accessibility",
      "Facebook",
      "X",
      "Instagram",
      "YouTube",
      "Take me there",
      "Stay on this page"
    ],
    "footer_tagline": "© BMW AG 2026"
  }
}